Metadata-Version: 1.1
Name: proxyalhttp
Version: 0.1
Summary: i love
Home-page: UNKNOWN
Author: you
Author-email: UNKNOWN
License: UNKNOWN
Platform: UNKNOWN
Classifier: Programming Language :: Python :: 3
Classifier: Operating System :: OS Independent
Classifier: License :: OSI Approved :: MIT License
